design.sv
module sr_flipflop (input clk,
                    input reset,
                    input S,
                    input R,
                    output reg Q,
                    output reg Qbar);
  always @(posedge clk or posedge reset) begin
    if (reset) begin
      Q <= 0;
      Qbar <= 1;
    end
    else begin
      case ({S, R})
        2'b00: ;
        2'b01: begin Q <= 0; Qbar <= 1; end
        2'b10: begin Q <= 1; Qbar <= 0; end
        2'b11: begin Q <= 1'bx; Qbar <= 1'bx; end
          endcase
        end
        end
        endmodule

testbench.sv
module tb_sr_flipflop;
  reg clk, reset, S, R;
  wire Q, Qbar;
  
  sr_flipflop uut (.clk(clk), .reset(reset), .S(S), .R(R), .Q(Q), .Qbar(Qbar));
  
  always #5 clk = ~clk;
  
  initial begin
    $dumpfile("sr_flipflop.vcd");
    $dumpvars;
    $monitor("Time=%0t | S=%b R=%b | Q=%b Qbar=%b", $time, S, R, Q, Qbar);
    
    clk = 0; reset = 1; S = 0; R = 0; #10;
    reset = 0;
    
    S = 1; R = 0; #10;
        S = 0; R = 1; #10;
        S = 0; R = 0; #10;
        S = 1; R = 1; #10;
    $finish;
  end
endmodule

sr_flipflop.vcd
$date
	Mon Jul 14 08:44:07 2025
$end
$version
	Icarus Verilog
$end
$timescale
	1s
$end
$scope module tb_sr_flipflop $end
$var wire 1 ! Qbar $end
$var wire 1 " Q $end
$var reg 1 # R $end
$var reg 1 $ S $end
$var reg 1 % clk $end
$var reg 1 & reset $end
$scope module uut $end
$var wire 1 # R $end
$var wire 1 $ S $end
$var wire 1 % clk $end
$var wire 1 & reset $end
$var reg 1 " Q $end
$var reg 1 ! Qbar $end
$upscope $end
$upscope $end
$enddefinitions $end
$comment Show the parameter values. $end
$dumpall
$end
#0
$dumpvars
1&
0%
0$
0#
0"
1!
$end
#5
1%
#10
0%
1$
0&
#15
0!
1"
1%
#20
0%
1#
0$
#25
1!
0"
1%
#30
0%
0#
#35
1%
#40
0%
1#
1$
#45
x!
x"
1%
